intelligen/AI.py
intelligen/__init__.py
intelligen/constants.py
intelligen/integrate.py
intelligen/intelligen.py
intelligen/interpolate.py
intelligen/linregress.py
intelligen/numeric.py
intelligen/signals.py
intelligen/stats/__init__.py
intelligen/stats/distributions.py
intelligen/stats/functions.py
intelligen-0.13.0.dist-info/LICENSE
intelligen-0.13.0.dist-info/METADATA
intelligen-0.13.0.dist-info/WHEEL
intelligen-0.13.0.dist-info/dependency_links.txt
intelligen-0.13.0.dist-info/top_level.txt
intelligen-0.13.0.dist-info/RECORD
