Metadata-Version: 2.1
Name: intelligen
Version: 0.13.0
Summary: This is a Python package for math and artificial intelligence tools
Home-page: https://github.com/Bouchet07/intelligen
Author: Diego Bouchet
Author-email: diegobouchet88@gmail.com
License: MIT license
Keywords: intelligen
Platform: UNKNOWN
Classifier: Development Status :: 2 - Pre-Alpha
Classifier: Intended Audience :: Developers
Classifier: License :: OSI Approved :: MIT License
Classifier: Natural Language :: English
Classifier: Programming Language :: Python :: 3
Classifier: Programming Language :: Python :: 3.5
Classifier: Programming Language :: Python :: 3.6
Classifier: Programming Language :: Python :: 3.7
Classifier: Programming Language :: Python :: 3.8
Requires-Python: >=3.5
License-File: LICENSE
Requires-Dist: numpy
Requires-Dist: matplotlib
